<?xml version="1.0" encoding="UTF-8"?>
<openerp>
    <data>

        <record id="report_quotation_std_xls" model="ir.actions.report.xml">
            <field name="name">Quotation STD(XLS)</field>
            <field name="type">ir.actions.report.xml</field>
            <field name="model">sale.order</field>
            <field name="report_name">quotation_std_xls</field>
            <field name="report_type">aeroo</field>
            <field name="in_format">oo-ods</field>
            <field name="out_format" eval="ref('report_aeroo.report_mimetypes_xls_odt')"/>
            <field name="parser_loc">report_quotation_std/report/parser.py</field>
            <field name="report_rml">report_quotaiton_std/report/quotation_std.ods</field>
            <field name="parser_state">loc</field>
            <field name="tml_source">file</field>
        </record>

        <ir_set>
            <field name="key" eval="'action'"/>
            <field name="key2" eval="'client_print_multi'"/>
            <field name="models" eval="['sale.order']"/>
            <field name="name">Quotation STD(XLS)</field>
            <field name="value" eval="'ir.actions.report.xml,'+str(report_quotation_std_xls)"/>
            <field name="isobject" eval="True"/>
            <field name="replace" eval="True"/>
        </ir_set>

        <record id="report_construction_order_pdf" model="ir.actions.report.xml">
            <field name="name">Construction Order (PDF)</field>
            <field name="type">ir.actions.report.xml</field>
            <field name="model">project.task</field>
            <field name="report_name">construction_order_pdf</field>
            <field name="report_type">aeroo</field>
            <field name="in_format">oo-ods</field>
            <field name="out_format" eval="ref('report_aeroo.report_mimetypes_pdf_odt')"/>
            <field name="parser_loc">report_task_construction_order/report/parser.py</field>
            <field name="report_rml">report_task_construction_order/report/construction_order.ods</field>
            <field name="parser_state">loc</field>
            <field name="tml_source">file</field>
        </record>

        <ir_set>
            <field name="key" eval="'action'"/>
            <field name="key2" eval="'client_print_multi'"/>
            <field name="models" eval="['project.task']"/>
            <field name="name">Construction Order (PDF)</field>
            <field name="value" eval="'ir.actions.report.xml,'+str(report_construction_order_pdf)"/>
            <field name="isobject" eval="True"/>
            <field name="replace" eval="True"/>
        </ir_set>

    </data>
</openerp>
